{
  "project_info": {
    "project_number": "939456751909",
    "project_id": "fir-7b7ba",
    "storage_bucket": "fir-7b7ba.appspot.com"
  },
  "client": [
    {
      "client_info": {
        "mobilesdk_app_id": "1:939456751909:android:0566d9e1dcf33f14a592cc",
        "android_client_info": {
          "package_name": "com.example.firebase"
        }
      },
      "oauth_client": [],
      "api_key": [
        {
          "current_key": "AIzaSyA1o_Cx6pZZja9wO1Ddn5HiDAIEMiKHgv0"
        }
      ],
      "services": {
        "appinvite_service": {
          "other_platform_oauth_client": []
        }
      }
    }
  ],
  "configuration_version": "1"
}